LICENSE
LICENSE.md
README.md
pyproject.toml
setup.py
urwid_readline/__init__.py
urwid_readline/readline_edit.py
urwid_readline/test_readline_edit.py
urwid_readline.egg-info/PKG-INFO
urwid_readline.egg-info/SOURCES.txt
urwid_readline.egg-info/dependency_links.txt
urwid_readline.egg-info/requires.txt
urwid_readline.egg-info/top_level.txt