Metadata-Version: 2.1
Name: urwid_readline
Version: 0.14
Summary: A textbox edit widget for urwid that supports readline shortcuts
Home-page: https://github.com/rr-/urwid_readline
Author: Marcin Kurczewski
Author-email: rr-@sakuya.pl
Classifier: Environment :: Console
Classifier: Development Status :: 4 - Beta
Classifier: Intended Audience :: Developers
Classifier: License :: OSI Approved :: MIT License
Classifier: Operating System :: OS Independent
Classifier: Operating System :: POSIX :: Linux
Classifier: Programming Language :: Python :: 3 :: Only
Classifier: Topic :: Desktop Environment
Classifier: Topic :: Software Development
Classifier: Topic :: Software Development :: Widget Sets
Classifier: Topic :: Software Development :: Libraries :: Python Modules
License-File: LICENSE
License-File: LICENSE.md
Requires-Dist: urwid
Provides-Extra: dev
Requires-Dist: black; extra == "dev"
Requires-Dist: pytest; extra == "dev"
